nonebot_plugin_statistical/__init__.py
nonebot_plugin_statistical/config.py
nonebot_plugin_statistical/statistical_handle.py
nonebot_plugin_statistical/statistical_hook.py
nonebot_plugin_statistical-0.4.4.dist-info/LICENSE
nonebot_plugin_statistical-0.4.4.dist-info/WHEEL
nonebot_plugin_statistical-0.4.4.dist-info/METADATA
nonebot_plugin_statistical-0.4.4.dist-info/RECORD
